pyrexia/__init__.py
pyrexia/__main__.py
pyrexia/action.py
pyrexia/config.py
pyrexia/control.py
pyrexia/dht_sensor_hook.py
pyrexia/error.py
pyrexia/irelay.py
pyrexia/mode.py
pyrexia/null_sensor_hook.py
pyrexia/program.py
pyrexia/relay.py
pyrexia/rest.py
pyrexia/sensor.py
pyrexia/sensor_hook.py
pyrexia/sp_sensor_hook.py
pyrexia/utils.py
pyrexia_stat-0.9.4.dist-info/LICENSE
pyrexia_stat-0.9.4.dist-info/METADATA
pyrexia_stat-0.9.4.dist-info/WHEEL
pyrexia_stat-0.9.4.dist-info/top_level.txt
pyrexia_stat-0.9.4.dist-info/RECORD
