Metadata-Version: 2.1
Name: pyrexia-stat
Version: 0.9.4
Summary: Thermostat runs on raspberry pi
Author-email: Edward McGrath <edward@edwardmcgrath.com>
Project-URL: Homepage, https://github.com/cryptomcgrath/pyrexia-stat
Classifier: Programming Language :: Python :: 3
Classifier: License :: OSI Approved :: MIT License
Classifier: Operating System :: OS Independent
Requires-Python: >3.7
License-File: LICENSE
Requires-Dist: bleak (>=0.19.5)
Requires-Dist: pytz (>=2022.2.1)
Requires-Dist: sensorpush-bleak (>=1.0.7)
Requires-Dist: RPi.GPIO (>=0.7.0)
Requires-Dist: Adafruit-DHT (>=1.4.0)
Requires-Dist: requests (>=2.25.1)
